picmd/__init__.py
picmd/_communicator.py
picmd/_const.py
picmd/_data.py
picmd/_exception.py
picmd/_handler.py
picmd/_picmd.py
picmd/_receiver.py
picmd/_register.py
picmd/_util.py
picmd/py.typed
picmd-0.7.0.dist-info/LICENSE.txt
picmd-0.7.0.dist-info/METADATA
picmd-0.7.0.dist-info/WHEEL
picmd-0.7.0.dist-info/top_level.txt
picmd-0.7.0.dist-info/RECORD
