Metadata-Version: 2.1
Name: picmd
Version: 0.7.0
Summary: Serial Communication Framework for Raspberry PI
Home-page: https://github.com/ushiboy/picmd
Author: ushiboy
License: MIT
Platform: UNKNOWN
Classifier: Programming Language :: Python :: 3
Classifier: License :: OSI Approved :: MIT License
Classifier: Operating System :: POSIX :: Linux
Requires-Python: >=3.7
Requires-Dist: pyserial (>=3.4)
